{
  "png": "36",
  "doc_page": 34,
  "discipline": "structural",
  "extract": true,
  "extraction": {
    "sheet_code": "S-07",
    "sheet_name": "แปลนโครงสร้างหลังคา",
    "pattern": "plan",
    "plan": [
      {
        "element_id": "ค1",
        "element_type": "beam",
        "count": 3,
        "grid_refs": [
          "A-1/A-2",
          "B-1/B-2",
          "C-1/C-2"
        ],
        "span_length_m": 8.5,
        "confidence_score": 0.7,
        "confidence_flags": [
          "count_uncertain"
        ]
      },
      {
        "element_id": "ต1",
        "element_type": "column",
        "count": 6,
        "grid_refs": [
          "A-1",
          "A-2",
          "B-1",
          "B-2",
          "C-1",
          "C-2"
        ],
        "height_mm": 3200,
        "confidence_score": 0.7,
        "confidence_flags": [
          "height_estimated_from_text"
        ]
      }
    ],
    "schedule": [],
    "section": [],
    "notes": {
      "concrete_strength_ksc": 240,
      "steel_main": "SD40",
      "steel_stirrup": "SR24",
      "cover_mm": {
        "beam": 25,
        "column": 25,
        "footing": 75
      },
      "lap_rule": "40D",
      "design_codes": [],
      "confidence_score": 0.6,
      "confidence_flags": [
        "inferred_from_standard_practice"
      ]
    },
    "warnings": [
      "No explicit rebar details or schedules provided on this sheet.",
      "Column height inferred from text description; not directly dimensioned."
    ]
  }
}