{
  "png": "25",
  "doc_page": 23,
  "discipline": "structural",
  "extract": true,
  "extraction": {
    "sheet_code": "S-04",
    "sheet_name": "แปลนคาน, พื้นชั้น 1",
    "pattern": "plan",
    "plan": [
      {
        "element_id": "B1",
        "element_type": "beam",
        "count": 6,
        "grid_refs": [
          "A-1/A-2",
          "A-2/A-3",
          "A-3/A-4",
          "B-1/B-2",
          "C-1/C-2",
          "D-1/D-2"
        ],
        "span_length_m": 3.2,
        "confidence_score": 0.8,
        "confidence_flags": []
      },
      {
        "element_id": "B2",
        "element_type": "beam",
        "count": 5,
        "grid_refs": [
          "B-2/B-3",
          "C-2/C-3",
          "D-2/D-3",
          "E-2/E-3",
          "F-2/F-3"
        ],
        "span_length_m": 3.2,
        "confidence_score": 0.8,
        "confidence_flags": []
      },
      {
        "element_id": "B2X",
        "element_type": "beam",
        "count": 4,
        "grid_refs": [
          "B-1/B-2",
          "C-1/C-2",
          "D-1/D-2",
          "E-1/E-2"
        ],
        "span_length_m": 3.2,
        "confidence_score": 0.7,
        "confidence_flags": [
          "count_uncertain"
        ]
      },
      {
        "element_id": "S1",
        "element_type": "slab",
        "count": 1,
        "grid_refs": [
          "A-1/A-2",
          "A-2/A-3",
          "A-3/A-4",
          "B-1/B-2",
          "B-2/B-3",
          "C-1/C-2",
          "C-2/C-3",
          "D-1/D-2",
          "D-2/D-3",
          "E-1/E-2",
          "E-2/E-3",
          "F-1/F-2",
          "F-2/F-3"
        ],
        "span_length_m": 9.6,
        "confidence_score": 0.7,
        "confidence_flags": [
          "span_estimated"
        ]
      }
    ],
    "schedule": [],
    "section": [],
    "notes": {},
    "warnings": []
  }
}