{
  "png": "47",
  "doc_page": 45,
  "discipline": "structural",
  "sheet_code": "S-19",
  "sheet_name": "ขยายการวางพื้นสำเร็จรูป SP แผนที่ 2/2",
  "pattern": "section",
  "schema_generation": "primary_rawjson_schema.md (2026-07-10 compiled)",
  "source_image": "image/บ้าน_เล็ก_2ชั้น_03/บ้าน_เล็ก_2ชั้น_03_หน้า47.png",
  "view_title": "4 precast plank (SP) placement condition details, sheet 2/2 (final structural sheet, S-19 of 19), all 1:20",
  "elements": [
    { "element_id": "SP_placement_cutoff_joint", "element_type": "precast_plank_placement_detail", "description": "ลักษณะการวางพื้น SP บริเวณรอยตัดขาด -- SP-to-SP joint at a cut-off line, sealed with silicone", "scale": "1:20", "dims_m": { "left_bay": 0.50, "right_bay": 0.50, "gap": 0.015 }, "topping_thickness_m": 0.05, "extra_mesh": [{ "dia_mm": 6, "type": "RB", "spacing_mm": 200 }], "joint_bar": [{ "count": 1, "dia_mm": 9, "type": "RB" }, { "count": 1, "dia_mm": 9, "type": "RB" }], "sealant": "SILICONE BUILDING SEALANTS", "plank_depth_m": 0.40, "confidence_score": 0.75, "confidence_flags": [] },
    { "element_id": "SP_cast_fill_edge_beam_gap", "element_type": "precast_plank_placement_detail", "description": "ลักษณะการหล่อพื้นเสริมกรณีเศษช่องว่างที่คานริม -- cast-in-place infill for leftover gap at edge beam", "scale": "1:20", "dims_m": { "max_gap": 0.60, "adjacent_bay": 0.40 }, "hook_bar": [{ "dia_mm": 9, "type": "RB", "spacing_mm": 200 }, { "dia_mm": 9, "type": "RB", "spacing_mm": 200 }], "topping": "คอนกรีต TOPPING", "confidence_score": 0.6, "confidence_flags": ["needs_human_review_zoom_required"] },
    { "element_id": "SP_placement_no_support_column_beam", "element_type": "precast_plank_placement_detail", "description": "ลักษณะการวางพื้น SP บริเวณเสาหรือคานที่ไม่มีที่รองรับ -- SP condition with no bearing support", "scale": "1:20", "dims_m": { "d1": 0.50, "d2": 0.15, "min_bearing": 0.10 }, "extra_mesh": { "dia_mm": 6, "type": "RB", "spacing_mm": 200 }, "additional_main_bar": { "count": 2, "dia_mm": 12, "type": "RB" }, "stirrup_or_tie": { "dia_mm": 12, "type": "RB", "spacing_mm": 200 }, "plank_depth_m": 0.40, "confidence_score": 0.65, "confidence_flags": ["unsupported_edge_condition_structurally_significant"] },
    { "element_id": "SP_different_level_condition", "element_type": "precast_plank_placement_detail", "description": "กรณียกระดับพื้นสำเร็จต่างระดับกัน -- two precast plank floors at different levels", "scale": "1:20", "dims_m": { "d1": 0.10, "d2": 0.15 }, "level_difference_note": "ระยะตามความต่างระดับ (5+20ซม.)", "topping_thickness_m": 0.05, "leveling_concrete": "คอนกรีตปรับระดับ", "topping": "คอนกรีต TOPPING", "joint_bar": { "count": 1, "dia_mm": 9, "type": "RB" }, "hook_bar": { "dia_mm": 9, "type": "RB", "spacing_mm": 200 }, "plank_depth_m": 0.40, "confidence_score": 0.7, "confidence_flags": ["level_difference_note_reads_as_(5+20cm)_not_a_range_like_houses_2-4s_(5-20cm)"] }
  ],
  "notes_text": "* หรือเป็นไปตามข้อกำหนดการวางพื้นสำเร็จรูปของผู้ผลิตโดยต้องไม่น้อยกว่า 0.05 ม.",
  "title_block": { "sheet_code": "S-19", "total_sheets": 19, "scale": "1:20", "date": "19/10/59", "drawing_no": "S58136" },
  "confidence_score": 0.68,
  "confidence_flags": [],
  "warnings": [
    "This is the final structural sheet (S-19 of 19). All 19 structural sheets (pages 29-47) plus grid master are now personally extracted for this house.",
    "This sheet's 'level difference' note reads '(5+20ซม.)' rather than the '(5-20ซม.)' range format seen on houses #2-#4's equivalent detail -- could be a plus sign misread as a dash or vice versa, or a genuine different notation; recorded as printed and flagged rather than normalized to match prior houses."
  ]
}
