{
  "png": "36",
  "doc_page": 34,
  "discipline": "structural",
  "sheet_code": "S-08",
  "sheet_name": "ขยายคาน คสล.",
  "pattern": "section",
  "schema_generation": "primary_rawjson_schema.md (2026-07-10 compiled)",
  "source_image": "image/บ้าน_เล็ก_2ชั้น_03/บ้าน_เล็ก_2ชั้น_03_หน้า36.png",
  "view_title": "ขยายคาน คสล. -- RC beam section expansion details, all 1:20",
  "elements": [
    { "element_id": "BX1", "element_type": "beam", "width_mm": 400, "height_mm": 400, "main_bar": { "top": { "count": 2, "dia_mm": 12, "type": "RB" }, "bottom": { "count": 2, "dia_mm": 12, "type": "RB" } }, "stirrup": { "dia_mm": 6, "type": "RB", "spacing_mm": null, "note": "ป.Ø6มม.@ตามแบบ -- spacing as per drawing" }, "confidence_score": 0.75, "confidence_flags": ["has_a_companion_section_view_X1-X1_on_this_same_sheet"] },
    { "element_id": "X1-X1_section", "element_type": "beam", "description": "section X1-X1, companion detail to BX1", "width_mm": 150, "height_mm": 300, "main_bar": { "top": { "count": 2, "dia_mm": 12, "type": "RB" }, "bottom": { "count": 2, "dia_mm": 12, "type": "RB" } }, "stirrup": { "dia_mm": 6, "type": "RB", "spacing_mm": 200 }, "confidence_score": 0.78, "confidence_flags": [] },
    { "element_id": "BX", "element_type": "beam", "width_mm": 150, "height_mm": 300, "main_bar": { "top": { "count": 2, "dia_mm": 12, "type": "RB" }, "bottom": { "count": 2, "dia_mm": 12, "type": "RB" } }, "stirrup": { "dia_mm": 6, "type": "RB", "spacing_mm": 200 }, "confidence_score": 0.82, "confidence_flags": [] },
    { "element_id": "B1", "element_type": "beam", "width_mm": 150, "height_mm": 400, "main_bar": { "top": { "count": 2, "dia_mm": 12, "type": "RB" }, "bottom": { "count": 2, "dia_mm": 12, "type": "RB" } }, "stirrup": { "dia_mm": 6, "type": "RB", "spacing_mm": 200 }, "confidence_score": 0.85, "confidence_flags": [] },
    { "element_id": "B2", "element_type": "beam", "width_mm": 200, "height_mm": 400, "main_bar": { "top": { "count": 2, "dia_mm": 16, "type": "RB" }, "bottom": { "count": 2, "dia_mm": 16, "type": "RB" } }, "stirrup": { "dia_mm": 6, "type": "RB", "spacing_mm": 200 }, "confidence_score": 0.85, "confidence_flags": [] },
    { "element_id": "B2X", "element_type": "beam", "width_mm": 200, "height_mm": 400, "main_bar": { "top": { "count": 2, "dia_mm": 16, "type": "RB", "note": "ต่อเนื่องจาก B2 -- continuous from B2" }, "bottom": { "count": 2, "dia_mm": 16, "type": "RB", "note": "ต่อเนื่องจาก B2" } }, "additional_bars": [{ "count": 1, "dia_mm": 16, "type": "RB", "note": "1-Ø16มม. ล้วงเข้า B2 ระยะ 1.00ม. -- hooked/embedded into B2 for 1.00m development length" }], "stirrup": { "dia_mm": 6, "type": "RB", "spacing_mm": 200 }, "confidence_score": 0.75, "confidence_flags": ["needs_human_review_zoom_required", "extra_development_length_bar_detail"] },
    { "element_id": "B3", "element_type": "beam", "width_mm": 200, "height_mm": 400, "main_bar": { "top": { "count": 2, "dia_mm": 16, "type": "RB" }, "bottom": { "count": 3, "dia_mm": 16, "type": "RB" } }, "stirrup": { "dia_mm": 6, "type": "RB", "spacing_mm": 200 }, "confidence_score": 0.85, "confidence_flags": ["ASYMMETRIC_main_bar_top2_bottom3"] },
    { "element_id": "B3X", "element_type": "beam", "width_mm": 200, "height_mm": 400, "main_bar": { "top": { "count": 2, "dia_mm": 16, "type": "RB", "note": "ต่อเนื่องจาก B3" }, "bottom": { "count": 2, "dia_mm": 16, "type": "RB", "note": "ต่อเนื่องจาก B3" } }, "additional_bars": [{ "count": 3, "dia_mm": 16, "type": "RB", "note": "3-Ø16มม. -- additional bottom bar, unclear if replacing or supplementing the continuous bars" }], "stirrup": { "dia_mm": 6, "type": "RB", "spacing_mm": 200 }, "confidence_score": 0.7, "confidence_flags": ["needs_human_review_zoom_required"] },
    { "element_id": "B4", "element_type": "beam", "width_mm": 200, "height_mm": 400, "main_bar": { "top": { "count": 3, "dia_mm": 16, "type": "RB" }, "bottom": { "count": 2, "dia_mm": 16, "type": "RB", "note": "หยุดที่ L/8 -- curtailed at L/8" } }, "additional_bars": [{ "count": 3, "dia_mm": 16, "type": "RB" }], "stirrup": { "dia_mm": 6, "type": "RB", "spacing_mm": 200 }, "confidence_score": 0.72, "confidence_flags": ["needs_human_review_zoom_required", "bottom_bar_carries_(หยุดที่_L/8)_curtailment_note_same_recurring_pattern_seen_in_houses_3_and_4"] },
    { "element_id": "B4X", "element_type": "beam", "width_mm": 200, "height_mm": 400, "main_bar": { "top": { "count": 2, "dia_mm": 16, "type": "RB", "note": "ต่อเนื่องจาก B4" }, "bottom": { "count": 2, "dia_mm": 16, "type": "RB", "note": "ต่อเนื่องจาก B4" } }, "stirrup": { "dia_mm": 6, "type": "RB", "spacing_mm": 200 }, "confidence_score": 0.78, "confidence_flags": [] },
    { "element_id": "B5", "element_type": "beam", "width_mm": 250, "height_mm": 500, "main_bar": { "top": { "count": 3, "dia_mm": 20, "type": "RB" }, "bottom": { "count": 3, "dia_mm": 20, "type": "RB", "note": "หยุดที่ L/8 -- curtailed at L/8" } }, "stirrup": { "dia_mm": 6, "type": "RB", "spacing_mm": 150 }, "confidence_score": 0.78, "confidence_flags": ["bottom_bar_carries_(หยุดที่_L/8)_curtailment_note"] },
    { "element_id": "RB1", "element_type": "tie_beam", "width_mm": 150, "height_mm": 400, "main_bar": { "top": { "count": 2, "dia_mm": 12, "type": "RB" }, "bottom": { "count": 2, "dia_mm": 12, "type": "RB" } }, "stirrup": { "dia_mm": 6, "type": "RB", "spacing_mm": 200 }, "confidence_score": 0.85, "confidence_flags": [] },
    { "element_id": "RB2", "element_type": "tie_beam", "width_mm": 150, "height_mm": 400, "main_bar": { "top": { "count": 2, "dia_mm": 16, "type": "RB" }, "bottom": { "count": 2, "dia_mm": 16, "type": "RB" } }, "stirrup": { "dia_mm": 6, "type": "RB", "spacing_mm": 200 }, "confidence_score": 0.85, "confidence_flags": [] },
    { "element_id": "RB3", "element_type": "tie_beam", "width_mm": 150, "height_mm": 400, "main_bar": { "top": { "count": 2, "dia_mm": 16, "type": "RB" }, "bottom": { "count": 2, "dia_mm": 20, "type": "RB" } }, "stirrup": { "dia_mm": 6, "type": "RB", "spacing_mm": 200 }, "confidence_score": 0.8, "confidence_flags": ["ASYMMETRIC_main_bar_diameter_top16_bottom20"] }
  ],
  "confidence_score": 0.8,
  "confidence_flags": [],
  "warnings": [
    "'หยุดที่ L/8' (curtailed at L/8) recurs on B4 and B5's bottom bars -- same recurring design-office detail pattern flagged in houses #3 and #4's equivalent beam sections (usually on a mark named B4). Continues to look like a genuine standard detail for this design office, not a misread.",
    "B2X/B3X/B4X sections describe bars as 'ต่อเนื่องจาก' (continuous from) their non-X counterpart (B2/B3/B4) but also list additional bar counts whose relationship to the continuous bars (replacing vs. supplementing) isn't fully clear from the section view alone -- flagged for human structural review rather than guessed.",
    "This sheet confirms the exact rebar specs referenced as 'spec_source: S-08' in the S-04/S-05/S-06 beam and tie-beam plans read earlier -- RB1/RB2/RB3 correspond to the tie-beam marks on S-06 (RB2/RB3 being heavier than perimeter RB1, confirmed here with larger bar diameters: RB1=2-Ø12mm, RB2=2-Ø16mm, RB3=2-Ø16mm top/2-Ø20mm bottom)."
  ]
}
