{
  "png": "49",
  "doc_page": 47,
  "discipline": "boq",
  "sheet_code": null,
  "sheet_name": "รายการประมาณราคาค่าก่อสร้าง บ้านครอบครัวไทยร่วมสมัย แบบที่ 2 (ฐานรากแผ่ ไม่มีระบบปรับอากาศ) - หมวดงานโครงสร้าง (แผ่นที่ 2/19)",
  "pattern": "material_list",
  "schema_generation": "primary_rawjson_schema.md (2026-07-10 compiled)",
  "source_image": "image/บ้าน_เล็ก_1ชั้น_02/บ้าน_เล็ก_1ชั้น_02_หน้า49.png",
  "sheet_no": "2/19",
  "categories": [
    { "category": "หมวดงานโครงสร้าง", "items": [
      { "item_no": "1", "description": "คอนกรีตพื้นบันได หนา 5 ซม. Wire Mesh Ø4mm.@0.20ม.#", "quantity": 74, "unit": "ตร.ม.", "material_unit_price": null, "material_amount": null, "labor_unit_price": null, "labor_amount": null, "total_amount": null, "confidence_score": 0.75, "confidence_flags": [] },
      { "item_no": null, "description": "พื้นคอนกรีตดาดฟ้ารูปแบบผิวเรียบ หนา 5 ซม.", "quantity": 74, "unit": "ตร.ม.", "material_unit_price": null, "material_amount": null, "labor_unit_price": null, "labor_amount": null, "total_amount": null, "confidence_score": 0.6, "confidence_flags": ["needs_human_review_zoom_required", "continuation_row_description_partially_legible"] },
      { "item_no": null, "description": "ฉาบผนังปูน", "quantity": 94, "unit": "ตร.ม.", "material_unit_price": null, "material_amount": null, "labor_unit_price": null, "labor_amount": null, "total_amount": null, "confidence_score": 0.55, "confidence_flags": ["needs_human_review_zoom_required"] },
      { "item_no": null, "description": "เหล็กเส้น SD40 Ø16 มม.", "quantity": 995, "unit": "กก.", "material_unit_price": null, "material_amount": null, "labor_unit_price": null, "labor_amount": null, "total_amount": null, "confidence_score": 0.85, "confidence_flags": [] },
      { "item_no": null, "description": "เหล็กเส้น SD40 Ø12 มม.", "quantity": 905, "unit": "กก.", "material_unit_price": null, "material_amount": null, "labor_unit_price": null, "labor_amount": null, "total_amount": null, "confidence_score": 0.85, "confidence_flags": [] },
      { "item_no": null, "description": "เหล็กเส้น SR24 Ø9 มม.", "quantity": 816, "unit": "กก.", "material_unit_price": null, "material_amount": null, "labor_unit_price": null, "labor_amount": null, "total_amount": null, "confidence_score": 0.85, "confidence_flags": [] },
      { "item_no": null, "description": "เหล็กเส้น SR24 Ø6 มม.", "quantity": 413, "unit": "กก.", "material_unit_price": null, "material_amount": null, "labor_unit_price": null, "labor_amount": null, "total_amount": null, "confidence_score": 0.85, "confidence_flags": [] },
      { "item_no": null, "description": "ตะปู", "quantity": 88, "unit": "กก.", "material_unit_price": null, "material_amount": null, "labor_unit_price": null, "labor_amount": null, "total_amount": null, "confidence_score": 0.85, "confidence_flags": [] },
      { "item_no": null, "description": "เศษไม้", "quantity": 43, "unit": "ตัว", "material_unit_price": null, "material_amount": null, "labor_unit_price": null, "labor_amount": null, "total_amount": null, "confidence_score": 0.6, "confidence_flags": ["unit_ตัว_uncertain_needs_human_review_zoom_required"] },
      { "item_no": null, "description": "ค้ำยันแบบหล่อคอนกรีต", "quantity": 85, "unit": "ลบ.ฟ.", "material_unit_price": null, "material_amount": null, "labor_unit_price": null, "labor_amount": null, "total_amount": null, "confidence_score": 0.6, "confidence_flags": ["unit_uncertain_needs_human_review_zoom_required"] },
      { "item_no": null, "description": "ไม้แบบหล่อคอนกรีต", "quantity": 352, "unit": "ตร.ม.", "material_unit_price": null, "material_amount": null, "labor_unit_price": null, "labor_amount": null, "total_amount": null, "confidence_score": 0.8, "confidence_flags": [] },
      { "item_no": null, "description": "คอนกรีตโครงสร้าง 1:2:4", "quantity": 282, "unit": "ลบ.ม.", "material_unit_price": null, "material_amount": null, "labor_unit_price": null, "labor_amount": null, "total_amount": null, "confidence_score": 0.8, "confidence_flags": [] },
      { "item_no": null, "description": "คอนกรีตหยาบ", "quantity": 29, "unit": "ลบ.ม.", "material_unit_price": null, "material_amount": null, "labor_unit_price": null, "labor_amount": null, "total_amount": null, "confidence_score": 0.8, "confidence_flags": [] },
      { "item_no": null, "description": "ทรายราดถม", "quantity": 1, "unit": "ลบ.ม.", "material_unit_price": null, "material_amount": null, "labor_unit_price": null, "labor_amount": null, "total_amount": null, "confidence_score": 0.65, "confidence_flags": ["needs_human_review_zoom_required"] },
      { "item_no": null, "description": "ทรายหยาบทั่วไป", "quantity": 5, "unit": "ลบ.ม.", "material_unit_price": null, "material_amount": null, "labor_unit_price": null, "labor_amount": null, "total_amount": null, "confidence_score": 0.65, "confidence_flags": ["needs_human_review_zoom_required"] },
      { "item_no": null, "description": "ซุปติน (ยาเสาเข็ม/หมุดหมาย -- uncertain term)", "quantity": 32, "unit": "ลบ.ม.", "material_unit_price": null, "material_amount": null, "labor_unit_price": null, "labor_amount": null, "total_amount": null, "confidence_score": 0.4, "confidence_flags": ["needs_human_review_zoom_required", "description_illegible_at_available_resolution_transcribed_phonetically_not_guessed_as_a_specific_material"] }
    ] }
  ],
  "confidence_score": 0.7,
  "confidence_flags": ["quantities_generally_clear_some_thai_unit/description_labels_less_legible_due_to_90_degree_rotation_and_small_font"],
  "warnings": [
    "Several continuation-row descriptions (items without their own item_no) were harder to read precisely due to the sheet's rotation and dense grid -- quantities themselves (the numeric column) were clearer and read with higher confidence than the Thai description text in several rows. Flagged individually rather than guessed."
  ]
}
