{
  "png": "70",
  "doc_page": 68,
  "discipline": "boq",
  "sheet_code": null,
  "sheet_name": "รายการประมาณราคาค่าก่อสร้าง บ้านครอบครัวไทยร่วมสมัย แบบที่ 3 (ฐานรากแผ่ ไม่มีระบบปรับอากาศ) - หมวดงานระบบสุขาภิบาล 3.1 งานระบบท่อโสโครก ท่อน้ำทิ้ง ท่ออากาศ ท่อน้ำฝน (แผ่นที่ 14/22)",
  "pattern": "material_list",
  "source_image": "image/บ้าน_เล็ก_2ชั้น_01/บ้าน_เล็ก_2ชั้น_01_หน้า70.png",
  "categories": [
    {
      "category": "หมวดงานระบบสุขาภิบาล",
      "items": [
        {
          "item_no": "3.1",
          "description": "งานระบบท่อโสโครก ท่อน้ำทิ้ง ท่ออากาศ ท่อน้ำฝน",
          "quantity": null,
          "unit": null,
          "material_unit_price": null,
          "material_amount": null,
          "labor_unit_price": null,
          "labor_amount": null,
          "total_amount": null,
          "confidence_score": 0.96,
          "confidence_flags": []
        },
        {
          "item_no": "3.1.1",
          "description": "งานเดินท่อโสโครก ท่อน้ำทิ้ง ท่ออากาศ ท่อน้ำฝน ( ท่อ PVC 8.5 )",
          "quantity": null,
          "unit": null,
          "material_unit_price": null,
          "material_amount": null,
          "labor_unit_price": null,
          "labor_amount": null,
          "total_amount": null,
          "confidence_score": 0.97,
          "confidence_flags": []
        },
        {
          "item_no": null,
          "description": "- ขนาด Dia. 1 1/2\"",
          "quantity": 12,
          "unit": "เมตร",
          "material_unit_price": null,
          "material_amount": null,
          "labor_unit_price": null,
          "labor_amount": null,
          "total_amount": null,
          "confidence_score": 0.98,
          "confidence_flags": []
        },
        {
          "item_no": null,
          "description": "- ขนาด Dia. 2\"",
          "quantity": 28,
          "unit": "เมตร",
          "material_unit_price": null,
          "material_amount": null,
          "labor_unit_price": null,
          "labor_amount": null,
          "total_amount": null,
          "confidence_score": 0.98,
          "confidence_flags": []
        },
        {
          "item_no": null,
          "description": "- ขนาด Dia. 2 1/2\"",
          "quantity": 8,
          "unit": "เมตร",
          "material_unit_price": null,
          "material_amount": null,
          "labor_unit_price": null,
          "labor_amount": null,
          "total_amount": null,
          "confidence_score": 0.98,
          "confidence_flags": []
        },
        {
          "item_no": null,
          "description": "- ขนาด Dia. 4\"",
          "quantity": 16,
          "unit": "เมตร",
          "material_unit_price": null,
          "material_amount": null,
          "labor_unit_price": null,
          "labor_amount": null,
          "total_amount": null,
          "confidence_score": 0.98,
          "confidence_flags": []
        },
        {
          "item_no": "3.1.2",
          "description": "ข้อต่อ ข้องอต่างๆ",
          "quantity": 1,
          "unit": "รวม",
          "material_unit_price": null,
          "material_amount": null,
          "labor_unit_price": null,
          "labor_amount": null,
          "total_amount": null,
          "confidence_score": 0.98,
          "confidence_flags": []
        },
        {
          "item_no": "3.1.3",
          "description": "อุปกรณ์ยึดและรองรับท่อ",
          "quantity": 1,
          "unit": "รวม",
          "material_unit_price": null,
          "material_amount": null,
          "labor_unit_price": null,
          "labor_amount": null,
          "total_amount": null,
          "confidence_score": 0.98,
          "confidence_flags": []
        },
        {
          "item_no": "3.1.4",
          "description": "ทดสอบ ทำความสะอาด ทาสี ทำสัญลักษณ์ท่อ",
          "quantity": 1,
          "unit": "รวม",
          "material_unit_price": null,
          "material_amount": null,
          "labor_unit_price": null,
          "labor_amount": null,
          "total_amount": null,
          "confidence_score": 0.98,
          "confidence_flags": []
        },
        {
          "item_no": "3.1.5",
          "description": "FCO",
          "quantity": null,
          "unit": null,
          "material_unit_price": null,
          "material_amount": null,
          "labor_unit_price": null,
          "labor_amount": null,
          "total_amount": null,
          "confidence_score": 0.97,
          "confidence_flags": []
        },
        {
          "item_no": null,
          "description": "- ขนาด Dia. 2\"",
          "quantity": 1,
          "unit": "ชุด",
          "material_unit_price": null,
          "material_amount": null,
          "labor_unit_price": null,
          "labor_amount": null,
          "total_amount": null,
          "confidence_score": 0.98,
          "confidence_flags": []
        },
        {
          "item_no": null,
          "description": "- ขนาด Dia. 4\"",
          "quantity": 1,
          "unit": "ชุด",
          "material_unit_price": null,
          "material_amount": null,
          "labor_unit_price": null,
          "labor_amount": null,
          "total_amount": null,
          "confidence_score": 0.98,
          "confidence_flags": []
        },
        {
          "item_no": "3.1.6",
          "description": "RFD. ขนาด Dia. 2 1/2\"",
          "quantity": 1,
          "unit": "ชุด",
          "material_unit_price": null,
          "material_amount": null,
          "labor_unit_price": null,
          "labor_amount": null,
          "total_amount": null,
          "confidence_score": 0.97,
          "confidence_flags": []
        },
        {
          "item_no": "3.1.7",
          "description": "FD ขนาด Dia. 2\"",
          "quantity": 2,
          "unit": "ชุด",
          "material_unit_price": null,
          "material_amount": null,
          "labor_unit_price": null,
          "labor_amount": null,
          "total_amount": null,
          "confidence_score": 0.98,
          "confidence_flags": []
        },
        {
          "item_no": "3.1.8",
          "description": "P-TRAP ขนาด Dia. 2\"",
          "quantity": 2,
          "unit": "ชุด",
          "material_unit_price": null,
          "material_amount": null,
          "labor_unit_price": null,
          "labor_amount": null,
          "total_amount": null,
          "confidence_score": 0.98,
          "confidence_flags": []
        },
        {
          "item_no": "3.1.9",
          "description": "AVC. ขนาด Dia. 2\"",
          "quantity": 1,
          "unit": "ชุด",
          "material_unit_price": null,
          "material_amount": null,
          "labor_unit_price": null,
          "labor_amount": null,
          "total_amount": null,
          "confidence_score": 0.97,
          "confidence_flags": []
        }
      ]
    }
  ],
  "confidence_score": 0.97,
  "confidence_flags": [],
  "warnings": [
    "PNG contains two portrait sheets side by side rotated 90 degrees; this is the physical LEFT half of the landscape scan (rotate 90 deg counter-clockwise to read), the higher-numbered sheet (14/22), paired with sheet 13/22 extracted as _1.json.",
    "Sub-category header on this detail sheet reads 'งานระบบท่อโสโครก ท่อน้ำทิ้ง ท่ออากาศ ท่อน้ำฝน' (ends in 'ท่อน้ำฝน' / rainwater pipe) which differs slightly from the shorter index-sheet wording 'งานระบบท่อโสโครก ท่อน้ำทิ้ง ท่ออากาศ ท่อ PVC 8.5' seen on sheet 13/22 - both transcribed exactly as printed on their respective sheets, not normalized to match.",
    "Item 3.1 continues onto the next PNG page (71) - item 3.1.10 and the 'รวมข้อ 3.1' subtotal row are on that sheet, see บ้าน_เล็ก_2ชั้น_01_หน้า71_1.json.",
    "All quantities re-verified at higher clarity (12, 28, 8, 16, 1, 1, 1, 1, 1, 1, 2, 2, 1)."
  ]
}
